tirmite/__init__.py
tirmite/_version.py
tirmite/cmd_tirmite.py
tirmite/hmmer_wrappers.py
tirmite/logs.py
tirmite/runBlastn.py
tirmite/tirmitetools.py
tirmite/utils.py
tirmite/wrapping.py
tirmite-1.2.0.dist-info/METADATA
tirmite-1.2.0.dist-info/WHEEL
tirmite-1.2.0.dist-info/entry_points.txt
tirmite-1.2.0.dist-info/licenses/LICENSE.txt
tirmite-1.2.0.dist-info/RECORD
