Metadata-Version: 2.4
Name: tirmite
Version: 1.2.0
Summary: Map TIR-pHMM models to genomic sequences for annotation of MITES and complete DNA-Transposons.
Project-URL: homepage, https://github.com/adamtaranto/TIRmite
Project-URL: documentation, https://github.com/adamtaranto/TIRmite
Project-URL: repository, https://github.com/adamtaranto/TIRmite
Author-email: Adam Taranto <adam.p.taranto@gmail.com>
License: MIT
License-File: LICENSE.txt
Classifier: Intended Audience :: Science/Research
Classifier: License :: OSI Approved :: MIT License
Classifier: Programming Language :: Python :: 3
Classifier: Topic :: Scientific/Engineering :: Bio-Informatics
Requires-Python: >=3.8
Requires-Dist: biopython>=1.70
Requires-Dist: pandas>=0.23.4
Requires-Dist: pymummer>=0.10.3
Requires-Dist: tsplit
Provides-Extra: dev
Requires-Dist: hatch; extra == 'dev'
Requires-Dist: ipykernel; extra == 'dev'
Requires-Dist: isort; extra == 'dev'
Requires-Dist: numpydoc-validation; extra == 'dev'
Requires-Dist: pre-commit; extra == 'dev'
Requires-Dist: pytest; extra == 'dev'
Requires-Dist: pytest-cov; extra == 'dev'
Requires-Dist: ruff; extra == 'dev'
